{
  "date": "2026-05-06",
  "order_count": 12,
  "buy_count": 7,
  "sell_count": 5,
  "orders": [
    {
      "symbol": "SHSE.688169",
      "side": "SELL",
      "volume": 800,
      "price": 114.39,
      "type": "limit"
    },
    {
      "symbol": "SHSE.600176",
      "side": "SELL",
      "volume": 2900,
      "price": 36.25,
      "type": "limit"
    },
    {
      "symbol": "SZSE.300782",
      "side": "SELL",
      "volume": 900,
      "price": 101.13,
      "type": "limit"
    },
    {
      "symbol": "SZSE.300347",
      "side": "SELL",
      "volume": 1600,
      "price": 52.9,
      "type": "limit"
    },
    {
      "symbol": "SZSE.000630",
      "side": "SELL",
      "volume": 14700,
      "price": 6.37,
      "type": "limit"
    },
    {
      "symbol": "SZSE.002475",
      "side": "BUY",
      "volume": 1300,
      "price": 68.43,
      "type": "limit"
    },
    {
      "symbol": "SHSE.600893",
      "side": "BUY",
      "volume": 1900,
      "price": 47.78,
      "type": "limit"
    },
    {
      "symbol": "SZSE.000938",
      "side": "BUY",
      "volume": 2900,
      "price": 32.49,
      "type": "limit"
    },
    {
      "symbol": "SHSE.601077",
      "side": "BUY",
      "volume": 12800,
      "price": 7.41,
      "type": "limit"
    },
    {
      "symbol": "SZSE.002625",
      "side": "BUY",
      "volume": 2300,
      "price": 40.88,
      "type": "limit"
    },
    {
      "symbol": "SZSE.003816",
      "side": "BUY",
      "volume": 20200,
      "price": 4.69,
      "type": "limit"
    },
    {
      "symbol": "SHSE.603893",
      "side": "BUY",
      "volume": 500,
      "price": 185.08,
      "type": "limit"
    }
  ]
}