{
  "overall": {
    "total_predictions": 11992,
    "mean": 0.981909,
    "std": 0.005058,
    "percentiles": {
      "p1": 0.965974,
      "p5": 0.972614,
      "p25": 0.97921,
      "p50": 0.982669,
      "p75": 0.98539,
      "p95": 0.988682,
      "p99": 0.990674
    }
  },
  "history": [
    {
      "date": "2026-04-03",
      "mean": 0.98253,
      "std": 0.00449,
      "min": 0.963604,
      "max": 0.992991,
      "bins": {
        "0.96-0.97": 5,
        "0.97-0.98": 66,
        "0.98-0.99": 221,
        "0.99-1.00": 8,
        "≥1.00": 0
      }
    },
    {
      "date": "2026-04-07",
      "mean": 0.982524,
      "std": 0.004671,
      "min": 0.96553,
      "max": 0.991183,
      "bins": {
        "0.96-0.97": 6,
        "0.97-0.98": 66,
        "0.98-0.99": 225,
        "0.99-1.00": 3,
        "≥1.00": 0
      }
    },
    {
      "date": "2026-04-08",
      "mean": 0.982463,
      "std": 0.004888,
      "min": 0.962394,
      "max": 0.992141,
      "bins": {
        "0.96-0.97": 5,
        "0.97-0.98": 81,
        "0.98-0.99": 205,
        "0.99-1.00": 9,
        "≥1.00": 0
      }
    },
    {
      "date": "2026-04-09",
      "mean": 0.981699,
      "std": 0.004989,
      "min": 0.961167,
      "max": 0.99061,
      "bins": {
        "0.96-0.97": 12,
        "0.97-0.98": 80,
        "0.98-0.99": 204,
        "0.99-1.00": 4,
        "≥1.00": 0
      }
    },
    {
      "date": "2026-04-10",
      "mean": 0.982443,
      "std": 0.004547,
      "min": 0.957677,
      "max": 0.990992,
      "bins": {
        "0.96-0.97": 3,
        "0.97-0.98": 72,
        "0.98-0.99": 220,
        "0.99-1.00": 4,
        "≥1.00": 0
      }
    },
    {
      "date": "2026-04-13",
      "mean": 0.982097,
      "std": 0.004414,
      "min": 0.963161,
      "max": 0.991649,
      "bins": {
        "0.96-0.97": 2,
        "0.97-0.98": 84,
        "0.98-0.99": 206,
        "0.99-1.00": 8,
        "≥1.00": 0
      }
    },
    {
      "date": "2026-04-14",
      "mean": 0.981883,
      "std": 0.00436,
      "min": 0.966832,
      "max": 0.991924,
      "bins": {
        "0.96-0.97": 4,
        "0.97-0.98": 85,
        "0.98-0.99": 209,
        "0.99-1.00": 2,
        "≥1.00": 0
      }
    },
    {
      "date": "2026-04-15",
      "mean": 0.981723,
      "std": 0.004462,
      "min": 0.968776,
      "max": 0.991365,
      "bins": {
        "0.96-0.97": 3,
        "0.97-0.98": 90,
        "0.98-0.99": 200,
        "0.99-1.00": 7,
        "≥1.00": 0
      }
    },
    {
      "date": "2026-04-16",
      "mean": 0.981177,
      "std": 0.004663,
      "min": 0.964489,
      "max": 0.991281,
      "bins": {
        "0.96-0.97": 7,
        "0.97-0.98": 99,
        "0.98-0.99": 191,
        "0.99-1.00": 3,
        "≥1.00": 0
      }
    },
    {
      "date": "2026-04-17",
      "mean": 0.981346,
      "std": 0.004927,
      "min": 0.959762,
      "max": 0.991257,
      "bins": {
        "0.96-0.97": 8,
        "0.97-0.98": 85,
        "0.98-0.99": 205,
        "0.99-1.00": 1,
        "≥1.00": 0
      }
    },
    {
      "date": "2026-04-20",
      "mean": 0.98154,
      "std": 0.005123,
      "min": 0.95581,
      "max": 0.989499,
      "bins": {
        "0.96-0.97": 8,
        "0.97-0.98": 89,
        "0.98-0.99": 201,
        "0.99-1.00": 0,
        "≥1.00": 0
      }
    },
    {
      "date": "2026-04-21",
      "mean": 0.980938,
      "std": 0.005561,
      "min": 0.95243,
      "max": 0.991456,
      "bins": {
        "0.96-0.97": 16,
        "0.97-0.98": 95,
        "0.98-0.99": 180,
        "0.99-1.00": 7,
        "≥1.00": 0
      }
    },
    {
      "date": "2026-04-22",
      "mean": 0.981192,
      "std": 0.005219,
      "min": 0.96041,
      "max": 0.991602,
      "bins": {
        "0.96-0.97": 12,
        "0.97-0.98": 94,
        "0.98-0.99": 189,
        "0.99-1.00": 4,
        "≥1.00": 0
      }
    },
    {
      "date": "2026-04-24",
      "mean": 0.981027,
      "std": 0.005514,
      "min": 0.952368,
      "max": 0.993358,
      "bins": {
        "0.96-0.97": 10,
        "0.97-0.98": 92,
        "0.98-0.99": 191,
        "0.99-1.00": 5,
        "≥1.00": 0
      }
    },
    {
      "date": "2026-04-27",
      "mean": 0.981397,
      "std": 0.005181,
      "min": 0.962387,
      "max": 0.992294,
      "bins": {
        "0.96-0.97": 10,
        "0.97-0.98": 95,
        "0.98-0.99": 190,
        "0.99-1.00": 4,
        "≥1.00": 0
      }
    },
    {
      "date": "2026-04-29",
      "mean": 0.981764,
      "std": 0.005009,
      "min": 0.96308,
      "max": 0.991233,
      "bins": {
        "0.96-0.97": 10,
        "0.97-0.98": 86,
        "0.98-0.99": 201,
        "0.99-1.00": 2,
        "≥1.00": 0
      }
    },
    {
      "date": "2026-04-30",
      "mean": 0.981994,
      "std": 0.004665,
      "min": 0.964624,
      "max": 0.991217,
      "bins": {
        "0.96-0.97": 3,
        "0.97-0.98": 85,
        "0.98-0.99": 206,
        "0.99-1.00": 5,
        "≥1.00": 0
      }
    },
    {
      "date": "2026-05-06",
      "mean": 0.982035,
      "std": 0.005045,
      "min": 0.964657,
      "max": 0.992216,
      "bins": {
        "0.96-0.97": 8,
        "0.97-0.98": 83,
        "0.98-0.99": 202,
        "0.99-1.00": 6,
        "≥1.00": 0
      }
    },
    {
      "date": "2026-05-07",
      "mean": 0.982029,
      "std": 0.004511,
      "min": 0.96462,
      "max": 0.991598,
      "bins": {
        "0.96-0.97": 3,
        "0.97-0.98": 80,
        "0.98-0.99": 215,
        "0.99-1.00": 2,
        "≥1.00": 0
      }
    },
    {
      "date": "2026-05-08",
      "mean": 0.982782,
      "std": 0.004002,
      "min": 0.971916,
      "max": 0.992109,
      "bins": {
        "0.96-0.97": 0,
        "0.97-0.98": 68,
        "0.98-0.99": 225,
        "0.99-1.00": 7,
        "≥1.00": 0
      }
    },
    {
      "date": "2026-05-11",
      "mean": 0.981991,
      "std": 0.004521,
      "min": 0.953278,
      "max": 0.992002,
      "bins": {
        "0.96-0.97": 3,
        "0.97-0.98": 84,
        "0.98-0.99": 209,
        "0.99-1.00": 3,
        "≥1.00": 0
      }
    },
    {
      "date": "2026-05-12",
      "mean": 0.981546,
      "std": 0.005003,
      "min": 0.959937,
      "max": 0.991282,
      "bins": {
        "0.96-0.97": 3,
        "0.97-0.98": 84,
        "0.98-0.99": 207,
        "0.99-1.00": 4,
        "≥1.00": 0
      }
    },
    {
      "date": "2026-05-13",
      "mean": 0.981415,
      "std": 0.004827,
      "min": 0.960625,
      "max": 0.992577,
      "bins": {
        "0.96-0.97": 4,
        "0.97-0.98": 94,
        "0.98-0.99": 192,
        "0.99-1.00": 10,
        "≥1.00": 0
      }
    },
    {
      "date": "2026-05-14",
      "mean": 0.982378,
      "std": 0.004887,
      "min": 0.961547,
      "max": 0.993647,
      "bins": {
        "0.96-0.97": 6,
        "0.97-0.98": 82,
        "0.98-0.99": 205,
        "0.99-1.00": 7,
        "≥1.00": 0
      }
    },
    {
      "date": "2026-05-15",
      "mean": 0.981941,
      "std": 0.005492,
      "min": 0.957598,
      "max": 0.991622,
      "bins": {
        "0.96-0.97": 15,
        "0.97-0.98": 73,
        "0.98-0.99": 207,
        "0.99-1.00": 4,
        "≥1.00": 0
      }
    },
    {
      "date": "2026-05-18",
      "mean": 0.981838,
      "std": 0.005428,
      "min": 0.956893,
      "max": 0.992605,
      "bins": {
        "0.96-0.97": 11,
        "0.97-0.98": 81,
        "0.98-0.99": 202,
        "0.99-1.00": 5,
        "≥1.00": 0
      }
    },
    {
      "date": "2026-05-19",
      "mean": 0.981198,
      "std": 0.005917,
      "min": 0.943316,
      "max": 0.99062,
      "bins": {
        "0.96-0.97": 18,
        "0.97-0.98": 77,
        "0.98-0.99": 198,
        "0.99-1.00": 6,
        "≥1.00": 0
      }
    },
    {
      "date": "2026-05-20",
      "mean": 0.982071,
      "std": 0.004864,
      "min": 0.962801,
      "max": 0.991334,
      "bins": {
        "0.96-0.97": 6,
        "0.97-0.98": 78,
        "0.98-0.99": 209,
        "0.99-1.00": 7,
        "≥1.00": 0
      }
    },
    {
      "date": "2026-05-21",
      "mean": 0.982012,
      "std": 0.005173,
      "min": 0.961318,
      "max": 0.991236,
      "bins": {
        "0.96-0.97": 8,
        "0.97-0.98": 84,
        "0.98-0.99": 201,
        "0.99-1.00": 7,
        "≥1.00": 0
      }
    },
    {
      "date": "2026-05-22",
      "mean": 0.982529,
      "std": 0.004753,
      "min": 0.958538,
      "max": 0.993612,
      "bins": {
        "0.96-0.97": 3,
        "0.97-0.98": 70,
        "0.98-0.99": 213,
        "0.99-1.00": 13,
        "≥1.00": 0
      }
    },
    {
      "date": "2026-05-25",
      "mean": 0.98252,
      "std": 0.004966,
      "min": 0.951968,
      "max": 0.992963,
      "bins": {
        "0.96-0.97": 4,
        "0.97-0.98": 71,
        "0.98-0.99": 212,
        "0.99-1.00": 12,
        "≥1.00": 0
      }
    },
    {
      "date": "2026-05-26",
      "mean": 0.982563,
      "std": 0.004835,
      "min": 0.963683,
      "max": 0.993384,
      "bins": {
        "0.96-0.97": 6,
        "0.97-0.98": 72,
        "0.98-0.99": 213,
        "0.99-1.00": 9,
        "≥1.00": 0
      }
    },
    {
      "date": "2026-05-27",
      "mean": 0.981751,
      "std": 0.005776,
      "min": 0.954855,
      "max": 0.993919,
      "bins": {
        "0.96-0.97": 9,
        "0.97-0.98": 78,
        "0.98-0.99": 205,
        "0.99-1.00": 5,
        "≥1.00": 0
      }
    },
    {
      "date": "2026-05-28",
      "mean": 0.982901,
      "std": 0.005079,
      "min": 0.955869,
      "max": 0.991056,
      "bins": {
        "0.96-0.97": 9,
        "0.97-0.98": 56,
        "0.98-0.99": 228,
        "0.99-1.00": 6,
        "≥1.00": 0
      }
    },
    {
      "date": "2026-05-29",
      "mean": 0.982121,
      "std": 0.005494,
      "min": 0.959635,
      "max": 0.992076,
      "bins": {
        "0.96-0.97": 12,
        "0.97-0.98": 69,
        "0.98-0.99": 213,
        "0.99-1.00": 5,
        "≥1.00": 0
      }
    },
    {
      "date": "2026-06-01",
      "mean": 0.981696,
      "std": 0.005421,
      "min": 0.955695,
      "max": 0.992306,
      "bins": {
        "0.96-0.97": 6,
        "0.97-0.98": 94,
        "0.98-0.99": 191,
        "0.99-1.00": 8,
        "≥1.00": 0
      }
    },
    {
      "date": "2026-06-02",
      "mean": 0.982127,
      "std": 0.005127,
      "min": 0.962124,
      "max": 0.991645,
      "bins": {
        "0.96-0.97": 12,
        "0.97-0.98": 70,
        "0.98-0.99": 211,
        "0.99-1.00": 7,
        "≥1.00": 0
      }
    },
    {
      "date": "2026-06-03",
      "mean": 0.981709,
      "std": 0.005711,
      "min": 0.95764,
      "max": 0.992318,
      "bins": {
        "0.96-0.97": 11,
        "0.97-0.98": 73,
        "0.98-0.99": 205,
        "0.99-1.00": 8,
        "≥1.00": 0
      }
    },
    {
      "date": "2026-06-04",
      "mean": 0.981278,
      "std": 0.0055,
      "min": 0.958258,
      "max": 0.990554,
      "bins": {
        "0.96-0.97": 12,
        "0.97-0.98": 88,
        "0.98-0.99": 196,
        "0.99-1.00": 3,
        "≥1.00": 0
      }
    },
    {
      "date": "2026-06-05",
      "mean": 0.982186,
      "std": 0.005586,
      "min": 0.954123,
      "max": 0.993444,
      "bins": {
        "0.96-0.97": 8,
        "0.97-0.98": 74,
        "0.98-0.99": 206,
        "0.99-1.00": 11,
        "≥1.00": 0
      }
    }
  ]
}